nthu_complaints_mcp/__init__.py
nthu_complaints_mcp/cli.py
nthu_complaints_mcp/exceptions.py
nthu_complaints_mcp/models.py
nthu_complaints_mcp/server.py
nthu_complaints_mcp-2.0.8.dist-info/METADATA
nthu_complaints_mcp-2.0.8.dist-info/WHEEL
nthu_complaints_mcp-2.0.8.dist-info/entry_points.txt
nthu_complaints_mcp-2.0.8.dist-info/licenses/LICENSE
nthu_complaints_mcp-2.0.8.dist-info/RECORD
