Metadata-Version: 2.4
Name: nthu-complaints-mcp
Version: 2.0.8
Summary: NTHU Complaints API Testing MCP Server - A powerful Model Context Protocol server for testing and interacting with NTHU complaint system APIs
Project-URL: Homepage, https://github.com/nthu-complaints/nthu-complaints-mcp
Project-URL: Documentation, https://github.com/nthu-complaints/nthu-complaints-mcp#readme
Project-URL: Repository, https://github.com/nthu-complaints/nthu-complaints-mcp.git
Project-URL: Issues, https://github.com/nthu-complaints/nthu-complaints-mcp/issues
Project-URL: Changelog, https://github.com/nthu-complaints/nthu-complaints-mcp/blob/main/CHANGELOG.md
Author: NTHU Complaints Team
Maintainer: NTHU Complaints Team
License: MIT License
License-File: LICENSE
Keywords: api-testing,complaints,fastmcp,mcp,model-context-protocol,nthu,student-services,university
Classifier: Development Status :: 4 - Beta
Classifier: Intended Audience :: Developers
Classifier: Intended Audience :: Education
Classifier: License :: OSI Approved :: MIT License
Classifier: Operating System :: OS Independent
Classifier: Programming Language :: Python :: 3
Classifier: Programming Language :: Python :: 3.8
Classifier: Programming Language :: Python :: 3.9
Classifier: Programming Language :: Python :: 3.10
Classifier: Programming Language :: Python :: 3.11
Classifier: Programming Language :: Python :: 3.12
Classifier: Topic :: Communications
Classifier: Topic :: Education
Classifier: Topic :: Internet :: WWW/HTTP :: HTTP Servers
Classifier: Topic :: Software Development :: Testing
Requires-Python: >=3.8
Requires-Dist: asyncio-mqtt>=0.11.0
Requires-Dist: click>=8.0.0
Requires-Dist: fastmcp>=0.2.0
Requires-Dist: httpx>=0.24.0
Requires-Dist: pydantic>=2.0.7
Requires-Dist: python-dotenv>=1.0.0
Requires-Dist: rich>=13.0.0
Provides-Extra: dev
Requires-Dist: black>=23.0.0; extra == 'dev'
Requires-Dist: flake8>=6.0.0; extra == 'dev'
Requires-Dist: isort>=5.12.0; extra == 'dev'
Requires-Dist: mypy>=1.0.0; extra == 'dev'
Requires-Dist: pre-commit>=3.0.0; extra == 'dev'
Requires-Dist: pytest-asyncio>=0.21.0; extra == 'dev'
Requires-Dist: pytest-httpx>=0.21.0; extra == 'dev'
Requires-Dist: pytest>=7.0.0; extra == 'dev'
Provides-Extra: test
Requires-Dist: pytest-asyncio>=0.21.0; extra == 'test'
Requires-Dist: pytest-cov>=4.0.0; extra == 'test'
Requires-Dist: pytest-httpx>=0.21.0; extra == 'test'
Requires-Dist: pytest>=7.0.0; extra == 'test'
